<?xml version="1.0" encoding="UTF-8" ?>
<wrapper><s>
  <w form="As" lemma="o" tag="DA0FP0" >As</w>
  <w form="pessoas" lemma="pessoa" tag="NCFP000" wnsyn="00007846-n" wnlex="XXX">pessoas</w>
  <w form="não" lemma="não" tag="RN" wnsyn="00118531-r" wnlex="XXX">não</w>
  <w form="lidas" lemma="ler" tag="VMP00PF" wnsyn="00625119-v" wnlex="XXX">lidas</w>
  <w form="em" lemma="em" tag="SP" wnsyn="xxx" wnlex="xxx">em</w>
  <w form="as" lemma="o" tag="DA0FP0" wnsyn="xxx" wnlex="xxx">as</w>
  <w form="mais" lemma="mais" tag="RG" wnsyn="00029367-r" wnlex="XXX">mais</w>
  <w form="repulsivas" lemma="repulsivo" tag="AQ0FP00" wnsyn="xxx" wnlex="xxx">repulsivas</w>
  <w form="páginas" lemma="página" tag="NCFP000" wnsyn="06256697-n" wnlex="XXX">páginas</w>
  <w form="que" lemma="que" tag="PR0CN00" wnsyn="xxx" wnlex="xxx">que</w>
  <w form="temos" lemma="ter" tag="VMIP1P0" wnsyn="00065639-v" wnlex="XXX">temos</w>
  <w form="de" lemma="de" tag="SP" wnsyn="xxx" wnlex="xxx">de</w>
  <w form="a" lemma="o" tag="DA0FS0" wnsyn="xxx" wnlex="xxx">a</w>
  <w form="história" lemma="história" tag="NCFS000" wnsyn="07221094-n" wnlex="XXX">história</w>
  <w form="de" lemma="de" tag="SP" wnsyn="xxx" wnlex="xxx">de</w>
  <w form="a" lemma="o" tag="DA0FS0" wnsyn="xxx" wnlex="xxx">a</w>
  <w form="humanidade" lemma="humanidade" tag="NCFS000" wnsyn="02472293-n" wnlex="XXX">humanidade</w>
  <w form=";" lemma=";" tag="Fx" wnsyn="xxx" wnlex="xxx">;</w>
  <w form="as" lemma="o" tag="DA0FP0" wnsyn="xxx" wnlex="xxx">as</w>
  <w form="que" lemma="que" tag="CS" wnsyn="xxx" wnlex="xxx">que</w>
  <w form="não" lemma="não" tag="RN" wnsyn="00118531-r" wnlex="XXX">não</w>
  <w form="viram" lemma="ver" tag="VMIS3P0" wnsyn="02130524-v" wnlex="XXX">viram</w>
  <w form="ainda" lemma="ainda" tag="RG" wnsyn="00047534-r" wnlex="XXX">ainda</w>
  <w form="nem" lemma="nem" tag="CC" wnsyn="xxx" wnlex="xxx">nem</w>
  <w form="coraram" lemma="corar" tag="VMIS3P0" wnsyn="00280301-v" wnlex="XXX">coraram</w>
  <w form="de" lemma="de" tag="SP" wnsyn="xxx" wnlex="xxx">de</w>
  <w form="ver" lemma="ver" tag="VMN0000" wnsyn="02130524-v" wnlex="XXX">ver</w>
  <w form="os" lemma="o" tag="DA0MP0" wnsyn="xxx" wnlex="xxx">os</w>
  <w form="irrefutáveis" lemma="irrefutável" tag="AQ0CP00" wnsyn="00591710-a" wnlex="XXX">irrefutáveis</w>
  <w form="e" lemma="e" tag="CC" wnsyn="xxx" wnlex="xxx">e</w>
  <w form="imorredouros" lemma="imorredouro" tag="AQ0MP00" wnsyn="xxx" wnlex="xxx">imorredouros</w>
  <w form="livros" lemma="livro" tag="NCMP000" wnsyn="02870092-n" wnlex="XXX">livros</w>
  <w form="de" lemma="de" tag="SP" wnsyn="xxx" wnlex="xxx">de</w>
  <w form="Alexandre_Herculano" lemma="alexandre_herculano" tag="NP00000" wnsyn="xxx" wnlex="xxx">Alexandre_Herculano</w>
  <w form="acerca" lemma="acercar" tag="VMIP3S0" wnsyn="02230772-v" wnlex="XXX">acerca</w>
  <w form="de" lemma="de" tag="SP" wnsyn="xxx" wnlex="xxx">de</w>
  <w form="a" lemma="o" tag="DA0FS0" wnsyn="xxx" wnlex="xxx">a</w>
  <w form="Inquisição" lemma="inquisição" tag="NP00000" wnsyn="07194676-n" wnlex="XXX">Inquisição</w>
  <w form="em" lemma="em" tag="SP" wnsyn="xxx" wnlex="xxx">em</w>
  <w form="Portugal" lemma="portugal" tag="NP00000" wnsyn="xxx" wnlex="xxx">Portugal</w>
  <w form="," lemma="," tag="Fc" wnsyn="xxx" wnlex="xxx">,</w>
  <w form="desculpavelmente" lemma="desculpavelmente" tag="RG" wnsyn="xxx" wnlex="xxx">desculpavelmente</w>
  <w form="malsinam" lemma="malsinar" tag="VMIP3P0" wnsyn="xxx" wnlex="xxx">malsinam</w>
  <w form="de" lemma="de" tag="SP" wnsyn="xxx" wnlex="xxx">de</w>
  <w form="inverosímil" lemma="inverosímil" tag="AQ0CS00" wnsyn="xxx" wnlex="xxx">inverosímil</w>
  <w form="o" lemma="o" tag="DA0MS0" wnsyn="xxx" wnlex="xxx">o</w>
  <w form="carácter" lemma="carácter" tag="NCMS000" wnsyn="06828818-n" wnlex="XXX">carácter</w>
  <w form="de" lemma="de" tag="SP" wnsyn="xxx" wnlex="xxx">de</w>
  <w form="Duarte_Cotinel" lemma="duarte_cotinel" tag="NP00000" wnsyn="xxx" wnlex="xxx">Duarte_Cotinel</w>
  <w form="." lemma="." tag="Fp" wnsyn="xxx" wnlex="xxx">.</w>
</s>
<s>
  <w form="Faz" lemma="fazer" tag="VMIP3S0" >Faz</w>
  <w form="lhes" lemma="lhe" tag="PP3CPD0" wnsyn="xxx" wnlex="xxx">lhes</w>
  <w form="honrosa" lemma="honroso" tag="AQ0FS00" wnsyn="xxx" wnlex="xxx">honrosa</w>
  <w form="repugnância" lemma="repugnância" tag="NCFS000" wnsyn="07503260-n" wnlex="XXX">repugnância</w>
  <w form="tão" lemma="tão" tag="RG" wnsyn="00022131-r" wnlex="XXX">tão</w>
  <w form="extremada" lemma="extremar" tag="VMP00SF" wnsyn="01535082-a" wnlex="XXX">extremada</w>
  <w form="infâmia" lemma="infâmia" tag="NCFS000" wnsyn="14441230-n" wnlex="XXX">infâmia</w>
  <w form="," lemma="," tag="Fc" wnsyn="xxx" wnlex="xxx">,</w>
  <w form="quando" lemma="quando" tag="RG" wnsyn="xxx" wnlex="xxx">quando</w>
  <w form="o" lemma="o" tag="DA0MS0" wnsyn="xxx" wnlex="xxx">o</w>
  <w form="intento" lemma="intento" tag="NCMS000" wnsyn="05982152-n" wnlex="XXX">intento</w>
  <w form="e" lemma="e" tag="CC" wnsyn="xxx" wnlex="xxx">e</w>
  <w form="fito" lemma="fito" tag="NCMS000" wnsyn="xxx" wnlex="xxx">fito</w>
  <w form="de" lemma="de" tag="SP" wnsyn="xxx" wnlex="xxx">de</w>
  <w form="ela" lemma="ele" tag="PP3FS00" wnsyn="xxx" wnlex="xxx">ela</w>
  <w form="é" lemma="ser" tag="VMIP3S0" wnsyn="02604760-v" wnlex="XXX">é</w>
  <w form="aferrar" lemma="aferrar" tag="VMN0000" wnsyn="01220303-v" wnlex="XXX">aferrar</w>
  <w form="de" lemma="de" tag="SP" wnsyn="xxx" wnlex="xxx">de</w>
  <w form="um" lemma="um" tag="DI0MS0" wnsyn="xxx" wnlex="xxx">um</w>
  <w form="cofre" lemma="cofre" tag="NCMS000" wnsyn="04340750-n" wnlex="XXX">cofre</w>
  <w form="recheado" lemma="rechear" tag="VMP00SM" wnsyn="00261533-v" wnlex="XXX">recheado</w>
  <w form="de" lemma="de" tag="SP" wnsyn="xxx" wnlex="xxx">de</w>
  <w form="riquezas" lemma="riqueza" tag="NCFP000" wnsyn="13353280-n" wnlex="XXX">riquezas</w>
  <w form="por" lemma="por" tag="SP" wnsyn="xxx" wnlex="xxx">por</w>
  <w form="cima" lemma="cima" tag="NCFS000" wnsyn="xxx" wnlex="xxx">cima</w>
  <w form="de" lemma="de" tag="SP" wnsyn="xxx" wnlex="xxx">de</w>
  <w form="a" lemma="o" tag="DA0FS0" wnsyn="xxx" wnlex="xxx">a</w>
  <w form="torrente" lemma="torrente" tag="NCFS000" wnsyn="00988320-n" wnlex="XXX">torrente</w>
  <w form="de" lemma="de" tag="SP" wnsyn="xxx" wnlex="xxx">de</w>
  <w form="lágrimas" lemma="lágrima" tag="NCFP000" wnsyn="05405324-n" wnlex="XXX">lágrimas</w>
  <w form="e" lemma="e" tag="CC" wnsyn="xxx" wnlex="xxx">e</w>
  <w form="sangue" lemma="sangue" tag="NCMS000" wnsyn="05399847-n" wnlex="XXX">sangue</w>
  <w form="de" lemma="de" tag="SP" wnsyn="xxx" wnlex="xxx">de</w>
  <w form="uma" lemma="um" tag="DI0FS0" wnsyn="xxx" wnlex="xxx">uma</w>
  <w form="família" lemma="família" tag="NCFS000" wnsyn="08101937-n" wnlex="XXX">família</w>
  <w form="," lemma="," tag="Fc" wnsyn="xxx" wnlex="xxx">,</w>
  <w form="por_cima_de" lemma="por_cima_de" tag="SP" wnsyn="xxx" wnlex="xxx">por_cima_de</w>
  <w form="uma" lemma="um" tag="DI0FS0" wnsyn="xxx" wnlex="xxx">uma</w>
  <w form="fogueira" lemma="fogueira" tag="NCFS000" wnsyn="07303335-n" wnlex="XXX">fogueira</w>
  <w form="que" lemma="que" tag="PR0CN00" wnsyn="xxx" wnlex="xxx">que</w>
  <w form="derrete" lemma="derreter" tag="VMIP3S0" wnsyn="00444629-v" wnlex="XXX">derrete</w>
  <w form="as" lemma="o" tag="DA0FP0" wnsyn="xxx" wnlex="xxx">as</w>
  <w form="carnes" lemma="carne" tag="NCFP000" wnsyn="07649854-n" wnlex="XXX">carnes</w>
  <w form="e" lemma="e" tag="CC" wnsyn="xxx" wnlex="xxx">e</w>
  <w form="pulveriza" lemma="pulverizar" tag="VMIP3S0" wnsyn="00330144-v" wnlex="XXX">pulveriza</w>
  <w form="os" lemma="o" tag="DA0MP0" wnsyn="xxx" wnlex="xxx">os</w>
  <w form="ossos" lemma="osso" tag="NCMP000" wnsyn="05269901-n" wnlex="XXX">ossos</w>
  <w form="de" lemma="de" tag="SP" wnsyn="xxx" wnlex="xxx">de</w>
  <w form="o" lemma="o" tag="DA0MS0" wnsyn="xxx" wnlex="xxx">o</w>
  <w form="possuidor" lemma="possuidor" tag="NCMS000" wnsyn="10389398-n" wnlex="XXX">possuidor</w>
  <w form="de" lemma="de" tag="SP" wnsyn="xxx" wnlex="xxx">de</w>
  <w form="o" lemma="o" tag="DA0MS0" wnsyn="xxx" wnlex="xxx">o</w>
  <w form="tesouro" lemma="tesouro" tag="NCMS000" wnsyn="13370669-n" wnlex="XXX">tesouro</w>
  <w form="." lemma="." tag="Fp" wnsyn="xxx" wnlex="xxx">.</w>
</s>
<s>
  <w form="Espantam" lemma="espantar" tag="VMIP3P0" >Espantam</w>
  <w form="se" lemma="se" tag="PP3CN00" wnsyn="xxx" wnlex="xxx">se</w>
  <w form="," lemma="," tag="Fc" wnsyn="xxx" wnlex="xxx">,</w>
  <w form="e" lemma="e" tag="CC" wnsyn="xxx" wnlex="xxx">e</w>
  <w form="refutam" lemma="refutar" tag="VMIP3P0" wnsyn="00814850-v" wnlex="XXX">refutam</w>
  <w form="de" lemma="de" tag="SP" wnsyn="xxx" wnlex="xxx">de</w>
  <w form="boa" lemma="bom" tag="AQ0FS00" wnsyn="01123148-a" wnlex="XXX">boa</w>
  <w form="fé" lemma="fé" tag="NCFS000" wnsyn="05941423-n" wnlex="XXX">fé</w>
  <w form="," lemma="," tag="Fc" wnsyn="xxx" wnlex="xxx">,</w>
  <w form="como" lemma="como" tag="CS" wnsyn="xxx" wnlex="xxx">como</w>
  <w form="desnaturais" lemma="desnatural" tag="AQ0CP00" wnsyn="xxx" wnlex="xxx">desnaturais</w>
  <w form="e" lemma="e" tag="CC" wnsyn="xxx" wnlex="xxx">e</w>
  <w form="insondáveis" lemma="insondável" tag="AQ0CP00" wnsyn="xxx" wnlex="xxx">insondáveis</w>
  <w form="os" lemma="o" tag="DA0MP0" wnsyn="xxx" wnlex="xxx">os</w>
  <w form="abismos" lemma="abismo" tag="NCMP000" wnsyn="09242389-n" wnlex="XXX">abismos</w>
  <w form="de" lemma="de" tag="SP" wnsyn="xxx" wnlex="xxx">de</w>
  <w form="infâmia" lemma="infâmia" tag="NCFS000" wnsyn="14441230-n" wnlex="XXX">infâmia</w>
  <w form="de" lemma="de" tag="SP" wnsyn="xxx" wnlex="xxx">de</w>
  <w form="onde" lemma="onde" tag="RG" wnsyn="xxx" wnlex="xxx">onde</w>
  <w form="lhes" lemma="lhe" tag="PP3CPD0" wnsyn="xxx" wnlex="xxx">lhes</w>
  <w form="sai" lemma="sair" tag="VMIP3S0" wnsyn="02009433-v" wnlex="XXX">sai</w>
  <w form="o" lemma="o" tag="DA0MS0" wnsyn="xxx" wnlex="xxx">o</w>
  <w form="homem" lemma="homem" tag="NCMS000" wnsyn="02472293-n" wnlex="XXX">homem</w>
  <w form="que" lemma="que" tag="PR0CN00" wnsyn="xxx" wnlex="xxx">que</w>
  <w form="não" lemma="não" tag="RN" wnsyn="00118531-r" wnlex="XXX">não</w>
  <w form="pode" lemma="poder" tag="VMIP3S0" wnsyn="xxx" wnlex="xxx">pode</w>
  <w form="alegar" lemma="alegar" tag="VMN0000" wnsyn="01016002-v" wnlex="XXX">alegar</w>
  <w form="como" lemma="como" tag="CS" wnsyn="xxx" wnlex="xxx">como</w>
  <w form="causa" lemma="causa" tag="NCFS000" wnsyn="09178999-n" wnlex="XXX">causa</w>
  <w form="de" lemma="de" tag="SP" wnsyn="xxx" wnlex="xxx">de</w>
  <w form="a" lemma="o" tag="DA0FS0" wnsyn="xxx" wnlex="xxx">a</w>
  <w form="morte" lemma="morte" tag="NCFS000" wnsyn="07355491-n" wnlex="XXX">morte</w>
  <w form="horrendíssima" lemma="horrendo" tag="AQDFS0" wnsyn="00364881-a" wnlex="XXX">horrendíssima</w>
  <w form="de" lemma="de" tag="SP" wnsyn="xxx" wnlex="xxx">de</w>
  <w form="uma" lemma="um" tag="DI0FS0" wnsyn="xxx" wnlex="xxx">uma</w>
  <w form="família" lemma="família" tag="NCFS000" wnsyn="08101937-n" wnlex="XXX">família</w>
  <w form="," lemma="," tag="Fc" wnsyn="xxx" wnlex="xxx">,</w>
  <w form="senão" lemma="senão" tag="RG" wnsyn="xxx" wnlex="xxx">senão</w>
  <w form="a" lemma="o" tag="DA0FS0" wnsyn="xxx" wnlex="xxx">a</w>
  <w form="necessidade" lemma="necessidade" tag="NCFS000" wnsyn="00023773-n" wnlex="XXX">necessidade</w>
  <w form="de" lemma="de" tag="SP" wnsyn="xxx" wnlex="xxx">de</w>
  <w form="a" lemma="o" tag="DA0FS0" wnsyn="xxx" wnlex="xxx">a</w>
  <w form="roubar" lemma="roubar" tag="VMN0000" wnsyn="02321757-v" wnlex="XXX">roubar</w>
  <w form="," lemma="," tag="Fc" wnsyn="xxx" wnlex="xxx">,</w>
  <w form="e" lemma="e" tag="CC" wnsyn="xxx" wnlex="xxx">e</w>
  <w form="a" lemma="o" tag="DA0FS0" wnsyn="xxx" wnlex="xxx">a</w>
  <w form="descoragem" lemma="descoragem" tag="NCFS000" wnsyn="xxx" wnlex="xxx">descoragem</w>
  <w form="para" lemma="para" tag="SP" wnsyn="xxx" wnlex="xxx">para</w>
  <w form="matá" lemma="matar" tag="VMN0000" wnsyn="xxx" wnlex="xxx">matá</w>
  <w form="a" lemma="o" tag="PP3FSA0" wnsyn="xxx" wnlex="xxx">a</w>
  <w form="a" lemma="o" tag="DA0FS0" wnsyn="xxx" wnlex="xxx">a</w>
  <w form="ferro" lemma="ferro" tag="NCMS000" wnsyn="14642417-n" wnlex="XXX">ferro</w>
  <w form="quando" lemma="quando" tag="RG" wnsyn="xxx" wnlex="xxx">quando</w>
  <w form="ela" lemma="ele" tag="PP3FS00" wnsyn="xxx" wnlex="xxx">ela</w>
  <w form="o" lemma="o" tag="PP3MSA0" wnsyn="xxx" wnlex="xxx">o</w>
  <w form="recebe" lemma="receber" tag="VMIP3S0" wnsyn="02210855-v" wnlex="XXX">recebe</w>
  <w form="em" lemma="em" tag="SP" wnsyn="xxx" wnlex="xxx">em</w>
  <w form="o" lemma="o" tag="DA0MS0" wnsyn="xxx" wnlex="xxx">o</w>
  <w form="seu" lemma="seu" tag="DP3MSS" wnsyn="xxx" wnlex="xxx">seu</w>
  <w form="grémio" lemma="grémio" tag="NCMS000" wnsyn="xxx" wnlex="xxx">grémio</w>
  <w form="confiadamente" lemma="confiado" tag="RG" wnsyn="xxx" wnlex="xxx">confiadamente</w>
  <w form="." lemma="." tag="Fp" wnsyn="xxx" wnlex="xxx">.</w>
</s>
<s>
  <w form="Espantam" lemma="espantar" tag="VMIP3P0" >Espantam</w>
  <w form="se" lemma="se" tag="PP3CN00" wnsyn="xxx" wnlex="xxx">se</w>
  <w form=";" lemma=";" tag="Fx" wnsyn="xxx" wnlex="xxx">;</w>
  <w form="mas" lemma="mas" tag="CC" wnsyn="xxx" wnlex="xxx">mas</w>
  <w form="não" lemma="não" tag="RN" wnsyn="00118531-r" wnlex="XXX">não</w>
  <w form="era" lemma="ser" tag="VMII1S0" wnsyn="02604760-v" wnlex="XXX">era</w>
  <w form="mais" lemma="mais" tag="RG" wnsyn="00029367-r" wnlex="XXX">mais</w>
  <w form="para" lemma="para" tag="SP" wnsyn="xxx" wnlex="xxx">para</w>
  <w form="assombros" lemma="assombro" tag="NCMP000" wnsyn="07510348-n" wnlex="XXX">assombros</w>
  <w form="Duarte_da_Paz" lemma="duarte_da_paz" tag="NP00000" wnsyn="xxx" wnlex="xxx">Duarte_da_Paz</w>
  <w form="," lemma="," tag="Fc" wnsyn="xxx" wnlex="xxx">,</w>
  <w form="aquele" lemma="aquele" tag="DD0MS0" wnsyn="xxx" wnlex="xxx">aquele</w>
  <w form="hebreu" lemma="hebreu" tag="NCMS000" wnsyn="xxx" wnlex="xxx">hebreu</w>
  <w form="que" lemma="que" tag="PR0CN00" wnsyn="xxx" wnlex="xxx">que</w>
  <w form="recebia" lemma="receber" tag="VMII3S0" wnsyn="02210855-v" wnlex="XXX">recebia</w>
  <w form="de" lemma="de" tag="SP" wnsyn="xxx" wnlex="xxx">de</w>
  <w form="os" lemma="o" tag="DA0MP0" wnsyn="xxx" wnlex="xxx">os</w>
  <w form="de" lemma="de" tag="SP" wnsyn="xxx" wnlex="xxx">de</w>
  <w form="a" lemma="o" tag="DA0FS0" wnsyn="xxx" wnlex="xxx">a</w>
  <w form="sua" lemma="seu" tag="DP3FSS" wnsyn="xxx" wnlex="xxx">sua</w>
  <w form="raça" lemma="raça" tag="NCFS000" wnsyn="07967982-n" wnlex="XXX">raça</w>
  <w form="ouro" lemma="ouro" tag="NCMS000" wnsyn="14638799-n" wnlex="XXX">ouro</w>
  <w form="a" lemma="a" tag="SP" wnsyn="xxx" wnlex="xxx">a</w>
  <w form="torrentes" lemma="torrente" tag="NCFP000" wnsyn="00988320-n" wnlex="XXX">torrentes</w>
  <w form="para" lemma="para" tag="SP" wnsyn="xxx" wnlex="xxx">para</w>
  <w form="os" lemma="o" tag="DA0MP0" wnsyn="xxx" wnlex="xxx">os</w>
  <w form="salvar" lemma="salvar" tag="VMN0000" wnsyn="02551144-v" wnlex="XXX">salvar</w>
  <w form="em" lemma="em" tag="SP" wnsyn="xxx" wnlex="xxx">em</w>
  <w form="Roma" lemma="roma" tag="NP00000" wnsyn="xxx" wnlex="xxx">Roma</w>
  <w form="," lemma="," tag="Fc" wnsyn="xxx" wnlex="xxx">,</w>
  <w form="e" lemma="e" tag="CC" wnsyn="xxx" wnlex="xxx">e</w>
  <w form="os" lemma="o" tag="PP3MPA0" wnsyn="xxx" wnlex="xxx">os</w>
  <w form="vendia" lemma="vender" tag="VMII3S0" wnsyn="02242464-v" wnlex="XXX">vendia</w>
  <w form="a" lemma="a" tag="SP" wnsyn="xxx" wnlex="xxx">a</w>
  <w form="os" lemma="o" tag="DA0MP0" wnsyn="xxx" wnlex="xxx">os</w>
  <w form="algozes" lemma="algoz" tag="NCMP000" wnsyn="10069427-n" wnlex="XXX">algozes</w>
  <w form="sagrados" lemma="sagrar" tag="VMP00PM" wnsyn="02053818-a" wnlex="XXX">sagrados</w>
  <w form="de" lemma="de" tag="SP" wnsyn="xxx" wnlex="xxx">de</w>
  <w form="D._João_III" lemma="d._joão_iii" tag="NP00000" wnsyn="xxx" wnlex="xxx">D._João_III</w>
  <w form="?" lemma="?" tag="Fit" wnsyn="xxx" wnlex="xxx">?</w>
</s>
<s>
  <w form="Não" lemma="não" tag="RN" wnsyn="00118531-r" wnlex="XXX">Não</w>
  <w form="era" lemma="ser" tag="VMII1S0" wnsyn="02604760-v" wnlex="XXX">era</w>
  <w form="mais" lemma="mais" tag="RG" wnsyn="00029367-r" wnlex="XXX">mais</w>
  <w form="incrível" lemma="incrível" tag="AQ0CS00" wnsyn="00645493-a" wnlex="XXX">incrível</w>
  <w form="a" lemma="o" tag="DA0FS0" wnsyn="xxx" wnlex="xxx">a</w>
  <w form="denúncia" lemma="denúncia" tag="NCFS000" wnsyn="07234230-n" wnlex="XXX">denúncia</w>
  <w form="de" lemma="de" tag="SP" wnsyn="xxx" wnlex="xxx">de</w>
  <w form="o" lemma="o" tag="DA0MS0" wnsyn="xxx" wnlex="xxx">o</w>
  <w form="parente" lemma="parente" tag="NCCS000" wnsyn="10235549-n" wnlex="XXX">parente</w>
  <w form="," lemma="," tag="Fc" wnsyn="xxx" wnlex="xxx">,</w>
  <w form="que" lemma="que" tag="PR0CN00" wnsyn="xxx" wnlex="xxx">que</w>
  <w form="esperava" lemma="esperar" tag="VMII3S0" wnsyn="01826723-v" wnlex="XXX">esperava</w>
  <w form="sonegar" lemma="sonegar" tag="VMN0000" wnsyn="xxx" wnlex="xxx">sonegar</w>
  <w form="a" lemma="a" tag="SP" wnsyn="xxx" wnlex="xxx">a</w>
  <w form="o" lemma="o" tag="DA0MS0" wnsyn="xxx" wnlex="xxx">o</w>
  <w form="confisco" lemma="confisco" tag="NCMS000" wnsyn="xxx" wnlex="xxx">confisco</w>
  <w form="de" lemma="de" tag="SP" wnsyn="xxx" wnlex="xxx">de</w>
  <w form="o" lemma="o" tag="DA0MS0" wnsyn="xxx" wnlex="xxx">o</w>
  <w form="Santo_Ofício" lemma="santo_ofício" tag="NP00000" wnsyn="xxx" wnlex="xxx">Santo_Ofício</w>
  <w form="os" lemma="o" tag="DA0MP0" wnsyn="xxx" wnlex="xxx">os</w>
  <w form="tesouros" lemma="tesouro" tag="NCMP000" wnsyn="13370669-n" wnlex="XXX">tesouros</w>
  <w form="de" lemma="de" tag="SP" wnsyn="xxx" wnlex="xxx">de</w>
  <w form="o" lemma="o" tag="DA0MS0" wnsyn="xxx" wnlex="xxx">o</w>
  <w form="irmão" lemma="irmão" tag="NCMS000" wnsyn="09876454-n" wnlex="XXX">irmão</w>
  <w form="," lemma="," tag="Fc" wnsyn="xxx" wnlex="xxx">,</w>
  <w form="e" lemma="e" tag="CC" wnsyn="xxx" wnlex="xxx">e</w>
  <w form="às_vezes" lemma="às_vezes" tag="RG" wnsyn="xxx" wnlex="xxx">às_vezes</w>
  <w form="de" lemma="de" tag="SP" wnsyn="xxx" wnlex="xxx">de</w>
  <w form="o" lemma="o" tag="DA0MS0" wnsyn="xxx" wnlex="xxx">o</w>
  <w form="pai" lemma="pai" tag="NCMS000" wnsyn="10080869-n" wnlex="XXX">pai</w>
  <w form="," lemma="," tag="Fc" wnsyn="xxx" wnlex="xxx">,</w>
  <w form="que" lemma="que" tag="PR0CN00" wnsyn="xxx" wnlex="xxx">que</w>
  <w form="expirava" lemma="expirar" tag="VMII3S0" wnsyn="00004227-v" wnlex="XXX">expirava</w>
  <w form="amaldiçoando" lemma="amaldiçoar" tag="VMG0000" wnsyn="00906735-v" wnlex="XXX">amaldiçoando</w>
  <w form="a" lemma="o" tag="DA0FS0" wnsyn="xxx" wnlex="xxx">a</w>
  <w form="cega" lemma="cego" tag="NCFS000" wnsyn="xxx" wnlex="xxx">cega</w>
  <w form="Providência" lemma="providência" tag="NP00000" wnsyn="01132327-n" wnlex="XXX">Providência</w>
  <w form="," lemma="," tag="Fc" wnsyn="xxx" wnlex="xxx">,</w>
  <w form="por" lemma="por" tag="SP" wnsyn="xxx" wnlex="xxx">por</w>
  <w form="não" lemma="não" tag="RN" wnsyn="00118531-r" wnlex="XXX">não</w>
  <w form="saber" lemma="saber" tag="VMN0000" wnsyn="00594621-v" wnlex="XXX">saber</w>
  <w form="quem" lemma="quem" tag="PT0CN00" wnsyn="xxx" wnlex="xxx">quem</w>
  <w form="o" lemma="o" tag="PP3MSA0" wnsyn="xxx" wnlex="xxx">o</w>
  <w form="chumbara" lemma="chumbar" tag="VMIM1S0" wnsyn="xxx" wnlex="xxx">chumbara</w>
  <w form="a" lemma="a" tag="SP" wnsyn="xxx" wnlex="xxx">a</w>
  <w form="as" lemma="o" tag="DA0FP0" wnsyn="xxx" wnlex="xxx">as</w>
  <w form="lajes" lemma="laje" tag="NCFP000" wnsyn="04233405-n" wnlex="XXX">lajes</w>
  <w form="que" lemma="que" tag="PR0CN00" wnsyn="xxx" wnlex="xxx">que</w>
  <w form="o" lemma="o" tag="DA0MS0" wnsyn="xxx" wnlex="xxx">o</w>
  <w form="sol" lemma="sol" tag="NCMS000" wnsyn="09450163-n" wnlex="XXX">sol</w>
  <w form="não" lemma="não" tag="RN" wnsyn="00118531-r" wnlex="XXX">não</w>
  <w form="aqueceu" lemma="aquecer" tag="VMIS3S0" wnsyn="00371264-v" wnlex="XXX">aqueceu</w>
  <w form="nunca" lemma="nunca" tag="RG" wnsyn="00020759-r" wnlex="XXX">nunca</w>
  <w form="?" lemma="?" tag="Fit" wnsyn="xxx" wnlex="xxx">?</w>
</s>
<s>
  <w form="O" lemma="o" tag="DA0MS0" >O</w>
  <w form="melhor" lemma="melhor" tag="AQ0CS00" wnsyn="00230335-a" wnlex="XXX">melhor</w>
  <w form="e" lemma="e" tag="CC" wnsyn="xxx" wnlex="xxx">e</w>
  <w form="mais" lemma="mais" tag="RG" wnsyn="00029367-r" wnlex="XXX">mais</w>
  <w form="alto" lemma="alto" tag="AQ0MS00" wnsyn="02385102-a" wnlex="XXX">alto</w>
  <w form="louvor" lemma="louvor" tag="NCMS000" wnsyn="06693198-n" wnlex="XXX">louvor</w>
  <w form="que" lemma="que" tag="PR0CN00" wnsyn="xxx" wnlex="xxx">que</w>
  <w form="pode" lemma="poder" tag="VMIP3S0" wnsyn="xxx" wnlex="xxx">pode</w>
  <w form="entoar" lemma="entoar" tag="VMN03S0" wnsyn="xxx" wnlex="xxx">entoar</w>
  <w form="se" lemma="se" tag="PP3CN00" wnsyn="xxx" wnlex="xxx">se</w>
  <w form="a" lemma="a" tag="SP" wnsyn="xxx" wnlex="xxx">a</w>
  <w form="este" lemma="este" tag="DD0MS0" wnsyn="xxx" wnlex="xxx">este</w>
  <w form="século" lemma="século" tag="NCMS000" wnsyn="15205532-n" wnlex="XXX">século</w>
  <w form="é" lemma="ser" tag="VMIP3S0" wnsyn="02604760-v" wnlex="XXX">é</w>
  <w form="não" lemma="não" tag="RN" wnsyn="00118531-r" wnlex="XXX">não</w>
  <w form="haver" lemma="haver" tag="VMN0000" wnsyn="02616713-v" wnlex="XXX">haver</w>
  <w form="aí" lemma="aí" tag="RG" wnsyn="00082308-r" wnlex="XXX">aí</w>
  <w form="quem" lemma="quem" tag="PR0CN00" wnsyn="xxx" wnlex="xxx">quem</w>
  <w form="já" lemma="já" tag="RG" wnsyn="00031798-r" wnlex="XXX">já</w>
  <w form="aceite" lemma="aceite" tag="AQ0CS00" wnsyn="xxx" wnlex="xxx">aceite</w>
  <w form="como" lemma="como" tag="CS" wnsyn="xxx" wnlex="xxx">como</w>
  <w form="praticáveis" lemma="praticar" tag="VMII2P0" wnsyn="02568672-v" wnlex="XXX">praticáveis</w>
  <w form="os" lemma="o" tag="DA0MP0" wnsyn="xxx" wnlex="xxx">os</w>
  <w form="atrozes" lemma="atroz" tag="AQ0CP00" wnsyn="01131454-a" wnlex="XXX">atrozes</w>
  <w form="lances" lemma="lance" tag="NCMP000" wnsyn="00105820-n" wnlex="XXX">lances</w>
  <w form="de" lemma="de" tag="SP" wnsyn="xxx" wnlex="xxx">de</w>
  <w form="um" lemma="um" tag="DI0MS0" wnsyn="xxx" wnlex="xxx">um</w>
  <w form="passado" lemma="passado" tag="NCMS000" wnsyn="15120823-n" wnlex="XXX">passado</w>
  <w form="," lemma="," tag="Fc" wnsyn="xxx" wnlex="xxx">,</w>
  <w form="que" lemma="que" tag="PR0CN00" wnsyn="xxx" wnlex="xxx">que</w>
  <w form="dista" lemma="distar" tag="VMIP3S0" wnsyn="xxx" wnlex="xxx">dista</w>
  <w form="de" lemma="de" tag="SP" wnsyn="xxx" wnlex="xxx">de</w>
  <w form="nós" lemma="nós" tag="PP1CP00" wnsyn="xxx" wnlex="xxx">nós</w>
  <w form="apenas" lemma="apenas" tag="RG" wnsyn="00003093-r" wnlex="XXX">apenas</w>
  <w form="século" lemma="século" tag="NCMS000" wnsyn="15205532-n" wnlex="XXX">século</w>
  <w form="e" lemma="e" tag="CC" wnsyn="xxx" wnlex="xxx">e</w>
  <w form="meio" lemma="meio" tag="NCMS000" wnsyn="00172710-n" wnlex="XXX">meio</w>
  <w form="." lemma="." tag="Fp" wnsyn="xxx" wnlex="xxx">.</w>
</s>
<s>
  <w form="Que" lemma="que" tag="CS" >Que</w>
  <w form="dias" lemma="dia" tag="NCMP000" wnsyn="15155220-n" wnlex="XXX">dias</w>
  <w form="aqueles" lemma="aquele" tag="PD0MP00" wnsyn="xxx" wnlex="xxx">aqueles</w>
  <w form="e" lemma="e" tag="CC" wnsyn="xxx" wnlex="xxx">e</w>
  <w form="que" lemma="que" tag="PT0CN00" wnsyn="xxx" wnlex="xxx">que</w>
  <w form="dias" lemma="dia" tag="NCMP000" wnsyn="15155220-n" wnlex="XXX">dias</w>
  <w form="os" lemma="o" tag="DA0MP0" wnsyn="xxx" wnlex="xxx">os</w>
  <w form="nossos" lemma="nosso" tag="DP1MPP" wnsyn="xxx" wnlex="xxx">nossos</w>
  <w form="!" lemma="!" tag="Fat" wnsyn="xxx" wnlex="xxx">!</w>
</s>
<s>
  <w form="Como" lemma="como" tag="CS" >Como</w>
  <w form="a" lemma="o" tag="DA0FS0" wnsyn="xxx" wnlex="xxx">a</w>
  <w form="vida" lemma="vida" tag="NCFS000" wnsyn="00017222-n" wnlex="XXX">vida</w>
  <w form="e" lemma="e" tag="CC" wnsyn="xxx" wnlex="xxx">e</w>
  <w form="alma" lemma="alma" tag="NCFS000" wnsyn="04632157-n" wnlex="XXX">alma</w>
  <w form="humana" lemma="humano" tag="AQ0FS00" wnsyn="01258617-a" wnlex="XXX">humana</w>
  <w form="eram" lemma="ser" tag="VMII3P0" wnsyn="02604760-v" wnlex="XXX">eram</w>
  <w form="então" lemma="então" tag="RG" wnsyn="xxx" wnlex="xxx">então</w>
  <w form="desgraçadas" lemma="desgraçar" tag="VMP00PF" wnsyn="01227546-a" wnlex="XXX">desgraçadas</w>
  <w form="!" lemma="!" tag="Fat" wnsyn="xxx" wnlex="xxx">!</w>
</s>
<s>
  <w form="Que" lemma="que" tag="PT0CN00" >Que</w>
  <w form="deploráveis" lemma="deplorável" tag="AQ0CP00" wnsyn="01126841-a" wnlex="XXX">deploráveis</w>
  <w form="gerações" lemma="geração" tag="NCFP000" wnsyn="02472987-n" wnlex="XXX">gerações</w>
  <w form="de" lemma="de" tag="SP" wnsyn="xxx" wnlex="xxx">de</w>
  <w form="infelizes" lemma="infeliz" tag="NCCP000" wnsyn="xxx" wnlex="xxx">infelizes</w>
  <w form="e" lemma="e" tag="CC" wnsyn="xxx" wnlex="xxx">e</w>
  <w form="de" lemma="de" tag="SP" wnsyn="xxx" wnlex="xxx">de</w>
  <w form="celerados" lemma="celerado" tag="NCMP000" wnsyn="xxx" wnlex="xxx">celerados</w>
  <w form="rolaram" lemma="rolar" tag="VMIS3P0" wnsyn="01391280-v" wnlex="XXX">rolaram</w>
  <w form="a" lemma="a" tag="SP" wnsyn="xxx" wnlex="xxx">a</w>
  <w form="a" lemma="o" tag="DA0FS0" wnsyn="xxx" wnlex="xxx">a</w>
  <w form="voragem" lemma="voragem" tag="NCFS000" wnsyn="07433145-n" wnlex="XXX">voragem</w>
  <w form="em" lemma="em" tag="SP" wnsyn="xxx" wnlex="xxx">em</w>
  <w form="correntes" lemma="corrente" tag="NCFP000" wnsyn="00038262-n" wnlex="XXX">correntes</w>
  <w form="de" lemma="de" tag="SP" wnsyn="xxx" wnlex="xxx">de</w>
  <w form="lama" lemma="lama" tag="NCFS000" wnsyn="14956661-n" wnlex="XXX">lama</w>
  <w form="ensanguentada" lemma="ensanguentar" tag="VMP00SF" wnsyn="00247993-a" wnlex="XXX">ensanguentada</w>
  <w form="!" lemma="!" tag="Fat" wnsyn="xxx" wnlex="xxx">!</w>
</s>
<s>
  <w form="Como" lemma="como" tag="CS" >Como</w>
  <w form="o" lemma="o" tag="DA0MS0" wnsyn="xxx" wnlex="xxx">o</w>
  <w form="sol" lemma="sol" tag="NCMS000" wnsyn="09450163-n" wnlex="XXX">sol</w>
  <w form="de" lemma="de" tag="SP" wnsyn="xxx" wnlex="xxx">de</w>
  <w form="Deus" lemma="deus" tag="NP00000" wnsyn="09505418-n" wnlex="XXX">Deus</w>
  <w form="passaria" lemma="passar" tag="VMIC3S0" wnsyn="01212230-v" wnlex="XXX">passaria</w>
  <w form="triste" lemma="triste" tag="AQ0CS00" wnsyn="00364479-a" wnlex="XXX">triste</w>
  <w form="em" lemma="em" tag="SP" wnsyn="xxx" wnlex="xxx">em</w>
  <w form="o" lemma="o" tag="DA0MS0" wnsyn="xxx" wnlex="xxx">o</w>
  <w form="céu" lemma="céu" tag="NCMS000" wnsyn="09436708-n" wnlex="XXX">céu</w>
  <w form="," lemma="," tag="Fc" wnsyn="xxx" wnlex="xxx">,</w>
  <w form="e" lemma="e" tag="CC" wnsyn="xxx" wnlex="xxx">e</w>
  <w form="o" lemma="o" tag="PD0MS00" wnsyn="xxx" wnlex="xxx">o</w>
  <w form="que" lemma="que" tag="PR0CN00" wnsyn="xxx" wnlex="xxx">que</w>
  <w form="iria" lemma="ir" tag="VMIC1S0" wnsyn="01835496-v" wnlex="XXX">iria</w>
  <w form="em" lemma="em" tag="SP" wnsyn="xxx" wnlex="xxx">em</w>
  <w form="o" lemma="o" tag="DA0MS0" wnsyn="xxx" wnlex="xxx">o</w>
  <w form="grande" lemma="grande" tag="AQ0CS00" wnsyn="01382086-a" wnlex="XXX">grande</w>
  <w form="Espírito_Criador" lemma="espírito_criador" tag="NP00000" wnsyn="xxx" wnlex="xxx">Espírito_Criador</w>
  <w form="," lemma="," tag="Fc" wnsyn="xxx" wnlex="xxx">,</w>
  <w form="lá" lemma="lá" tag="RG" wnsyn="00082308-r" wnlex="XXX">lá</w>
  <w form="em" lemma="em" tag="SP" wnsyn="xxx" wnlex="xxx">em</w>
  <w form="cima" lemma="cima" tag="NCFS000" wnsyn="xxx" wnlex="xxx">cima</w>
  <w form="," lemma="," tag="Fc" wnsyn="xxx" wnlex="xxx">,</w>
  <w form="cortinas" lemma="cortinar" tag="VMIP2S0" wnsyn="xxx" wnlex="xxx">cortinas</w>
  <w form="adentro" lemma="adentro" tag="RG" wnsyn="00110815-r" wnlex="XXX">adentro</w>
  <w form="de" lemma="de" tag="SP" wnsyn="xxx" wnlex="xxx">de</w>
  <w form="estes" lemma="este" tag="DD0MP0" wnsyn="xxx" wnlex="xxx">estes</w>
  <w form="milhões" lemma="milhão" tag="NCCP000" wnsyn="13776432-n" wnlex="XXX">milhões</w>
  <w form="de" lemma="de" tag="SP" wnsyn="xxx" wnlex="xxx">de</w>
  <w form="estrelas" lemma="estrela" tag="NCFP000" wnsyn="09444100-n" wnlex="XXX">estrelas</w>
  <w form="!" lemma="!" tag="Fat" wnsyn="xxx" wnlex="xxx">!</w>
</s>
<s>
  <w form="É" lemma="ser" tag="VMIP3S0" wnsyn="02604760-v" wnlex="XXX">É</w>
  <w form="preciso" lemma="preciso" tag="AQ0MS00" wnsyn="00021766-a" wnlex="XXX">preciso</w>
  <w form="levar" lemma="levar" tag="VMN0000" wnsyn="00723545-v" wnlex="XXX">levar</w>
  <w form="o" lemma="o" tag="DA0MS0" wnsyn="xxx" wnlex="xxx">o</w>
  <w form="pensamento" lemma="pensamento" tag="NCMS000" wnsyn="05833840-n" wnlex="XXX">pensamento</w>
  <w form="a" lemma="a" tag="SP" wnsyn="xxx" wnlex="xxx">a</w>
  <w form="o" lemma="o" tag="DA0MS0" wnsyn="xxx" wnlex="xxx">o</w>
  <w form="âmago" lemma="âmago" tag="NCMS000" wnsyn="xxx" wnlex="xxx">âmago</w>
  <w form="," lemma="," tag="Fc" wnsyn="xxx" wnlex="xxx">,</w>
  <w form="a" lemma="a" tag="SP" wnsyn="xxx" wnlex="xxx">a</w>
  <w form="o" lemma="o" tag="DA0MS0" wnsyn="xxx" wnlex="xxx">o</w>
  <w form="turbilhão" lemma="turbilhão" tag="NCMS000" wnsyn="07433145-n" wnlex="XXX">turbilhão</w>
  <w form="de" lemma="de" tag="SP" wnsyn="xxx" wnlex="xxx">de</w>
  <w form="aqueles" lemma="aquele" tag="DD0MP0" wnsyn="xxx" wnlex="xxx">aqueles</w>
  <w form="dois" lemma="2" tag="Z" wnsyn="xxx" wnlex="xxx">dois</w>
  <w form="séculos" lemma="século" tag="NCMP000" wnsyn="15205532-n" wnlex="XXX">séculos</w>
  <w form="nefastos" lemma="nefasto" tag="AQ0MP00" wnsyn="00993529-a" wnlex="XXX">nefastos</w>
  <w form="que" lemma="que" tag="PR0CN00" wnsyn="xxx" wnlex="xxx">que</w>
  <w form="marcam" lemma="marcar" tag="VMIP3P0" wnsyn="00508032-v" wnlex="XXX">marcam</w>
  <w form="o" lemma="o" tag="DA0MS0" wnsyn="xxx" wnlex="xxx">o</w>
  <w form="nosso" lemma="nosso" tag="DP1MSP" wnsyn="xxx" wnlex="xxx">nosso</w>
  <w form="opróbrio" lemma="opróbrio" tag="NCMS000" wnsyn="xxx" wnlex="xxx">opróbrio</w>
  <w form="desde" lemma="desde" tag="SP" wnsyn="xxx" wnlex="xxx">desde</w>
  <w form="D._João_III" lemma="d._joão_iii" tag="NP00000" wnsyn="xxx" wnlex="xxx">D._João_III</w>
  <w form="até" lemma="até" tag="RG" wnsyn="00027918-r" wnlex="XXX">até</w>
  <w form="a" lemma="a" tag="SP" wnsyn="xxx" wnlex="xxx">a</w>
  <w form="o" lemma="o" tag="DA0MS0" wnsyn="xxx" wnlex="xxx">o</w>
  <w form="marquês" lemma="marquês" tag="NCMS000" wnsyn="10295479-n" wnlex="XXX">marquês</w>
  <w form="de" lemma="de" tag="SP" wnsyn="xxx" wnlex="xxx">de</w>
  <w form="Pombal" lemma="pombal" tag="NP00000" wnsyn="03228692-n" wnlex="XXX">Pombal</w>
  <w form="," lemma="," tag="Fc" wnsyn="xxx" wnlex="xxx">,</w>
  <w form="aurora" lemma="aurora" tag="NCFS000" wnsyn="15168790-n" wnlex="XXX">aurora</w>
  <w form="de" lemma="de" tag="SP" wnsyn="xxx" wnlex="xxx">de</w>
  <w form="o" lemma="o" tag="DA0MS0" wnsyn="xxx" wnlex="xxx">o</w>
  <w form="melhor" lemma="melhor" tag="AQ0CS00" wnsyn="00230335-a" wnlex="XXX">melhor</w>
  <w form="dia" lemma="dia" tag="NCMS000" wnsyn="15155220-n" wnlex="XXX">dia</w>
  <w form="," lemma="," tag="Fc" wnsyn="xxx" wnlex="xxx">,</w>
  <w form="aurora" lemma="aurora" tag="NCFS000" wnsyn="15168790-n" wnlex="XXX">aurora</w>
  <w form="manchada" lemma="manchar" tag="VMP00SF" wnsyn="01537409-v" wnlex="XXX">manchada</w>
  <w form="ainda" lemma="ainda" tag="RG" wnsyn="00047534-r" wnlex="XXX">ainda</w>
  <w form="de" lemma="de" tag="SP" wnsyn="xxx" wnlex="xxx">de</w>
  <w form="laivos" lemma="laivo" tag="NCMP000" wnsyn="xxx" wnlex="xxx">laivos</w>
  <w form="de" lemma="de" tag="SP" wnsyn="xxx" wnlex="xxx">de</w>
  <w form="sangue" lemma="sangue" tag="NCMS000" wnsyn="05399847-n" wnlex="XXX">sangue</w>
  <w form="," lemma="," tag="Fc" wnsyn="xxx" wnlex="xxx">,</w>
  <w form="mas" lemma="mas" tag="CC" wnsyn="xxx" wnlex="xxx">mas</w>
  <w form="enfim" lemma="enfim" tag="RG" wnsyn="00047903-r" wnlex="XXX">enfim</w>
  <w form="o" lemma="o" tag="DA0MS0" wnsyn="xxx" wnlex="xxx">o</w>
  <w form="alvorecer" lemma="alvorecer" tag="VMN0000" wnsyn="02609614-v" wnlex="XXX">alvorecer</w>
  <w form="," lemma="," tag="Fc" wnsyn="xxx" wnlex="xxx">,</w>
  <w form="o" lemma="o" tag="DA0MS0" wnsyn="xxx" wnlex="xxx">o</w>
  <w form="redimir" lemma="redimir" tag="VMN0000" wnsyn="02520509-v" wnlex="XXX">redimir</w>
  <w form="—" lemma="—" tag="Fz" wnsyn="xxx" wnlex="xxx">—</w>
  <w form="se" lemma="se" tag="PP3CN00" wnsyn="xxx" wnlex="xxx">se</w>
  <w form="o" lemma="o" tag="DA0MS0" wnsyn="xxx" wnlex="xxx">o</w>
  <w form="homem" lemma="homem" tag="NCMS000" wnsyn="02472293-n" wnlex="XXX">homem</w>
  <w form="," lemma="," tag="Fc" wnsyn="xxx" wnlex="xxx">,</w>
  <w form="esquecido" lemma="esquecer" tag="VMP00SM" wnsyn="00610167-v" wnlex="XXX">esquecido</w>
  <w form="de" lemma="de" tag="SP" wnsyn="xxx" wnlex="xxx">de</w>
  <w form="Cristo" lemma="cristo" tag="NP00000" wnsyn="xxx" wnlex="xxx">Cristo</w>
  <w form="," lemma="," tag="Fc" wnsyn="xxx" wnlex="xxx">,</w>
  <w form="começou" lemma="começar" tag="VMIS3S0" wnsyn="02608347-v" wnlex="XXX">começou</w>
  <w form="então" lemma="então" tag="RG" wnsyn="xxx" wnlex="xxx">então</w>
  <w form="," lemma="," tag="Fc" wnsyn="xxx" wnlex="xxx">,</w>
  <w form="em" lemma="em" tag="SP" wnsyn="xxx" wnlex="xxx">em</w>
  <w form="este" lemma="este" tag="DD0MS0" wnsyn="xxx" wnlex="xxx">este</w>
  <w form="recanto" lemma="recanto" tag="NCMS000" wnsyn="03109881-n" wnlex="XXX">recanto</w>
  <w form="de" lemma="de" tag="SP" wnsyn="xxx" wnlex="xxx">de</w>
  <w form="heróis" lemma="herói" tag="NCMP000" wnsyn="10173086-n" wnlex="XXX">heróis</w>
  <w form="piratas" lemma="pirata" tag="AQ0CP00" wnsyn="xxx" wnlex="xxx">piratas</w>
  <w form="," lemma="," tag="Fc" wnsyn="xxx" wnlex="xxx">,</w>
  <w form="e" lemma="e" tag="CC" wnsyn="xxx" wnlex="xxx">e</w>
  <w form="de" lemma="de" tag="SP" wnsyn="xxx" wnlex="xxx">de</w>
  <w form="apóstolos" lemma="apóstolo" tag="NCMP000" wnsyn="10016103-n" wnlex="XXX">apóstolos</w>
  <w form="sanguinários" lemma="sanguinário" tag="NCMP000" wnsyn="xxx" wnlex="xxx">sanguinários</w>
  <w form="!" lemma="!" tag="Fat" wnsyn="xxx" wnlex="xxx">!</w>
</s>
<s>
  <w form="E" lemma="e" tag="CC" >E</w>
  <w form="a" lemma="o" tag="DA0FS0" wnsyn="xxx" wnlex="xxx">a</w>
  <w form="Providência" lemma="providência" tag="NP00000" wnsyn="01132327-n" wnlex="XXX">Providência</w>
  <w form="não" lemma="não" tag="RN" wnsyn="00118531-r" wnlex="XXX">não</w>
  <w form="contava" lemma="contar" tag="VMII3S0" wnsyn="00953216-v" wnlex="XXX">contava</w>
  <w form="como" lemma="como" tag="CS" wnsyn="xxx" wnlex="xxx">como</w>
  <w form="seus" lemma="seu" tag="AP0MP3P" wnsyn="xxx" wnlex="xxx">seus</w>
  <w form="," lemma="," tag="Fc" wnsyn="xxx" wnlex="xxx">,</w>
  <w form="como" lemma="como" tag="CS" wnsyn="xxx" wnlex="xxx">como</w>
  <w form="obra" lemma="obra" tag="NCFS000" wnsyn="xxx" wnlex="xxx">obra</w>
  <w form="sua" lemma="seu" tag="AP0FS3S" wnsyn="xxx" wnlex="xxx">sua</w>
  <w form="," lemma="," tag="Fc" wnsyn="xxx" wnlex="xxx">,</w>
  <w form="como" lemma="como" tag="CS" wnsyn="xxx" wnlex="xxx">como</w>
  <w form="filhos" lemma="filho" tag="NCMP000" wnsyn="10624074-n" wnlex="XXX">filhos</w>
  <w form="de" lemma="de" tag="SP" wnsyn="xxx" wnlex="xxx">de</w>
  <w form="a" lemma="o" tag="DA0FS0" wnsyn="xxx" wnlex="xxx">a</w>
  <w form="sua" lemma="seu" tag="DP3FSS" wnsyn="xxx" wnlex="xxx">sua</w>
  <w form="eternidade" lemma="eternidade" tag="NCFS000" wnsyn="13956905-n" wnlex="XXX">eternidade</w>
  <w form="aqueles" lemma="aquele" tag="DD0MP0" wnsyn="xxx" wnlex="xxx">aqueles</w>
  <w form="dois" lemma="2" tag="Z" wnsyn="xxx" wnlex="xxx">dois</w>
  <w form="séculos" lemma="século" tag="NCMP000" wnsyn="15205532-n" wnlex="XXX">séculos</w>
  <w form="?" lemma="?" tag="Fit" wnsyn="xxx" wnlex="xxx">?</w>
</s>
<s>
  <w form="A" lemma="o" tag="DA0FS0" >A</w>
  <w form="Providência" lemma="providência" tag="NP00000" wnsyn="01132327-n" wnlex="XXX">Providência</w>
  <w form="deixava" lemma="deixar" tag="VMII3S0" wnsyn="00120316-v" wnlex="XXX">deixava</w>
  <w form="escabujar" lemma="escabujar" tag="VMN0000" wnsyn="xxx" wnlex="xxx">escabujar</w>
  <w form="o" lemma="o" tag="DA0MS0" wnsyn="xxx" wnlex="xxx">o</w>
  <w form="hebreu" lemma="hebreu" tag="NCMS000" wnsyn="xxx" wnlex="xxx">hebreu</w>
  <w form="em" lemma="em" tag="SP" wnsyn="xxx" wnlex="xxx">em</w>
  <w form="as" lemma="o" tag="DA0FP0" wnsyn="xxx" wnlex="xxx">as</w>
  <w form="correntes" lemma="corrente" tag="NCFP000" wnsyn="00038262-n" wnlex="XXX">correntes</w>
  <w form="de" lemma="de" tag="SP" wnsyn="xxx" wnlex="xxx">de</w>
  <w form="a" lemma="o" tag="DA0FS0" wnsyn="xxx" wnlex="xxx">a</w>
  <w form="sua" lemma="seu" tag="DP3FSS" wnsyn="xxx" wnlex="xxx">sua</w>
  <w form="masmorra" lemma="masmorra" tag="NCFS000" wnsyn="02991302-n" wnlex="XXX">masmorra</w>
  <w form="," lemma="," tag="Fc" wnsyn="xxx" wnlex="xxx">,</w>
  <w form="e" lemma="e" tag="CC" wnsyn="xxx" wnlex="xxx">e</w>
  <w form="deixava" lemma="deixar" tag="VMII3S0" wnsyn="00120316-v" wnlex="XXX">deixava</w>
  <w form="aquecer" lemma="aquecer" tag="VMN03S0" wnsyn="xxx" wnlex="xxx">aquecer</w>
  <w form="se" lemma="se" tag="PP3CN00" wnsyn="xxx" wnlex="xxx">se</w>
  <w form="o" lemma="o" tag="DA0MS0" wnsyn="xxx" wnlex="xxx">o</w>
  <w form="frade" lemma="frade" tag="NCMS000" wnsyn="10111903-n" wnlex="XXX">frade</w>
  <w form="a" lemma="a" tag="SP" wnsyn="xxx" wnlex="xxx">a</w>
  <w form="as" lemma="o" tag="DA0FP0" wnsyn="xxx" wnlex="xxx">as</w>
  <w form="chamas" lemma="chama" tag="NCFP000" wnsyn="13480848-n" wnlex="XXX">chamas</w>
  <w form="crepitantes" lemma="crepitante" tag="AQ0CP00" wnsyn="xxx" wnlex="xxx">crepitantes</w>
  <w form="de" lemma="de" tag="SP" wnsyn="xxx" wnlex="xxx">de</w>
  <w form="os" lemma="o" tag="DA0MP0" wnsyn="xxx" wnlex="xxx">os</w>
  <w form="seus" lemma="seu" tag="DP3MPS" wnsyn="xxx" wnlex="xxx">seus</w>
  <w form="cruentos" lemma="cruentos" tag="NCMP000" wnsyn="xxx" wnlex="xxx">cruentos</w>
  <w form="holocaustos" lemma="holocausto" tag="NCMP000" wnsyn="xxx" wnlex="xxx">holocaustos</w>
  <w form="a" lemma="a" tag="SP" wnsyn="xxx" wnlex="xxx">a</w>
  <w form="Jesus" lemma="jesus" tag="NP00000" wnsyn="xxx" wnlex="xxx">Jesus</w>
  <w form="." lemma="." tag="Fp" wnsyn="xxx" wnlex="xxx">.</w>
</s>
<s>
  <w form="Mas" lemma="mas" tag="CC" >Mas</w>
  <w form="um" lemma="um" tag="DI0MS0" wnsyn="xxx" wnlex="xxx">um</w>
  <w form="dia" lemma="dia" tag="NCMS000" wnsyn="15155220-n" wnlex="XXX">dia</w>
  <w form="," lemma="," tag="Fc" wnsyn="xxx" wnlex="xxx">,</w>
  <w form="a" lemma="o" tag="DA0FS0" wnsyn="xxx" wnlex="xxx">a</w>
  <w form="última" lemma="último" tag="AO0FS00" wnsyn="01010271-a" wnlex="XXX">última</w>
  <w form="fogueira" lemma="fogueira" tag="NCFS000" wnsyn="07303335-n" wnlex="XXX">fogueira</w>
  <w form="devia" lemma="dever" tag="VMII3S0" wnsyn="02254155-v" wnlex="XXX">devia</w>
  <w form="apagar" lemma="apagar" tag="VMN03S0" wnsyn="xxx" wnlex="xxx">apagar</w>
  <w form="se" lemma="se" tag="PP3CN00" wnsyn="xxx" wnlex="xxx">se</w>
  <w form="devorando" lemma="devorar" tag="VMG0000" wnsyn="01173208-v" wnlex="XXX">devorando</w>
  <w form="o" lemma="o" tag="DA0MS0" wnsyn="xxx" wnlex="xxx">o</w>
  <w form="mais" lemma="mais" tag="RG" wnsyn="00029367-r" wnlex="XXX">mais</w>
  <w form="fanático" lemma="fanático" tag="AQ0MS00" wnsyn="01726859-a" wnlex="XXX">fanático</w>
  <w form="de" lemma="de" tag="SP" wnsyn="xxx" wnlex="xxx">de</w>
  <w form="os" lemma="o" tag="DA0MP0" wnsyn="xxx" wnlex="xxx">os</w>
  <w form="tonsurados" lemma="tonsurado" tag="NCMP000" wnsyn="xxx" wnlex="xxx">tonsurados</w>
  <w form="," lemma="," tag="Fc" wnsyn="xxx" wnlex="xxx">,</w>
  <w form="o" lemma="o" tag="DA0MS0" wnsyn="xxx" wnlex="xxx">o</w>
  <w form="padre" lemma="padre" tag="NCMS000" wnsyn="10471250-n" wnlex="XXX">padre</w>
  <w form="que" lemma="que" tag="PR0CN00" wnsyn="xxx" wnlex="xxx">que</w>
  <w form="em" lemma="em" tag="SP" wnsyn="xxx" wnlex="xxx">em</w>
  <w form="si" lemma="si" tag="PP3CSO0" wnsyn="xxx" wnlex="xxx">si</w>
  <w form="compendiava" lemma="compendiar" tag="VMII3S0" wnsyn="xxx" wnlex="xxx">compendiava</w>
  <w form="o" lemma="o" tag="DA0MS0" wnsyn="xxx" wnlex="xxx">o</w>
  <w form="ascetismo" lemma="ascetismo" tag="NCMS000" wnsyn="xxx" wnlex="xxx">ascetismo</w>
  <w form="fraudulento" lemma="fraudulento" tag="AQ0MS00" wnsyn="01160584-a" wnlex="XXX">fraudulento</w>
  <w form="," lemma="," tag="Fc" wnsyn="xxx" wnlex="xxx">,</w>
  <w form="as" lemma="o" tag="DA0FP0" wnsyn="xxx" wnlex="xxx">as</w>
  <w form="ilustrações" lemma="ilustração" tag="NCFP000" wnsyn="03931044-n" wnlex="XXX">ilustrações</w>
  <w form="fictícias" lemma="fictício" tag="AQ0FP00" wnsyn="02727706-a" wnlex="XXX">fictícias</w>
  <w form="de" lemma="de" tag="SP" wnsyn="xxx" wnlex="xxx">de</w>
  <w form="o" lemma="o" tag="DA0MS0" wnsyn="xxx" wnlex="xxx">o</w>
  <w form="alto" lemma="alto" tag="AQ0MS00" wnsyn="02385102-a" wnlex="XXX">alto</w>
  <w form="," lemma="," tag="Fc" wnsyn="xxx" wnlex="xxx">,</w>
  <w form="os" lemma="o" tag="DA0MP0" wnsyn="xxx" wnlex="xxx">os</w>
  <w form="dons" lemma="dom" tag="NCMP000" wnsyn="05624042-n" wnlex="XXX">dons</w>
  <w form="falazes" lemma="falaz" tag="AQ0CP00" wnsyn="00633084-a" wnlex="XXX">falazes</w>
  <w form="de" lemma="de" tag="SP" wnsyn="xxx" wnlex="xxx">de</w>
  <w form="inspirado" lemma="inspirado" tag="NCMS000" wnsyn="xxx" wnlex="xxx">inspirado</w>
  <w form="," lemma="," tag="Fc" wnsyn="xxx" wnlex="xxx">,</w>
  <w form="as" lemma="o" tag="DA0FP0" wnsyn="xxx" wnlex="xxx">as</w>
  <w form="raivas" lemma="raiva" tag="NCFP000" wnsyn="07516354-n" wnlex="XXX">raivas</w>
  <w form="teocráticas" lemma="teocráticas" tag="AQ0FP00" wnsyn="xxx" wnlex="xxx">teocráticas</w>
  <w form="," lemma="," tag="Fc" wnsyn="xxx" wnlex="xxx">,</w>
  <w form="quantos" lemma="quanto" tag="PT0MP00" wnsyn="xxx" wnlex="xxx">quantos</w>
  <w form="herpes" lemma="herpes" tag="NCMN000" wnsyn="01338685-n" wnlex="XXX">herpes</w>
  <w form="tinham" lemma="ter" tag="VMII3P0" wnsyn="00065639-v" wnlex="XXX">tinham</w>
  <w form="roído" lemma="roer" tag="VMP00SM" wnsyn="01446420-v" wnlex="XXX">roído</w>
  <w form="e" lemma="e" tag="CC" wnsyn="xxx" wnlex="xxx">e</w>
  <w form="empeçonhado" lemma="empeçonhar" tag="VMP00SM" wnsyn="01323338-v" wnlex="XXX">empeçonhado</w>
  <w form="os" lemma="o" tag="DA0MP0" wnsyn="xxx" wnlex="xxx">os</w>
  <w form="liames" lemma="liame" tag="NCMP000" wnsyn="03673971-n" wnlex="XXX">liames</w>
  <w form="que" lemma="que" tag="PR0CN00" wnsyn="xxx" wnlex="xxx">que</w>
  <w form="suavemente" lemma="suave" tag="RG" wnsyn="xxx" wnlex="xxx">suavemente</w>
  <w form="enlaçavam" lemma="enlaçar" tag="VMII3P0" wnsyn="01517662-v" wnlex="XXX">enlaçavam</w>
  <w form="a" lemma="o" tag="DA0FS0" wnsyn="xxx" wnlex="xxx">a</w>
  <w form="humanidade" lemma="humanidade" tag="NCFS000" wnsyn="02472293-n" wnlex="XXX">humanidade</w>
  <w form="com" lemma="com" tag="SP" wnsyn="xxx" wnlex="xxx">com</w>
  <w form="a" lemma="o" tag="DA0FS0" wnsyn="xxx" wnlex="xxx">a</w>
  <w form="cruz" lemma="cruz" tag="NCFS000" wnsyn="03135152-n" wnlex="XXX">cruz</w>
  <w form="de" lemma="de" tag="SP" wnsyn="xxx" wnlex="xxx">de</w>
  <w form="o" lemma="o" tag="DA0MS0" wnsyn="xxx" wnlex="xxx">o</w>
  <w form="seu" lemma="seu" tag="DP3MSS" wnsyn="xxx" wnlex="xxx">seu</w>
  <w form="mais" lemma="mais" tag="RG" wnsyn="00029367-r" wnlex="XXX">mais</w>
  <w form="divino" lemma="divino" tag="AQ0MS00" wnsyn="01180363-a" wnlex="XXX">divino</w>
  <w form="redentor" lemma="redentor" tag="NCMS000" wnsyn="xxx" wnlex="xxx">redentor</w>
  <w form="." lemma="." tag="Fp" wnsyn="xxx" wnlex="xxx">.</w>
</s>
<s>
  <w form="Um" lemma="um" tag="DI0MS0" >Um</w>
  <w form="dia" lemma="dia" tag="NCMS000" wnsyn="15155220-n" wnlex="XXX">dia</w>
  <w form="acendeu" lemma="acender" tag="VMIS3S0" wnsyn="xxx" wnlex="xxx">acendeu</w>
  <w form="se" lemma="se" tag="PP3CN00" wnsyn="xxx" wnlex="xxx">se</w>
  <w form="uma" lemma="um" tag="DI0FS0" wnsyn="xxx" wnlex="xxx">uma</w>
  <w form="fogueira" lemma="fogueira" tag="NCFS000" wnsyn="07303335-n" wnlex="XXX">fogueira</w>
  <w form=";" lemma=";" tag="Fx" wnsyn="xxx" wnlex="xxx">;</w>
  <w form="e" lemma="e" tag="CC" wnsyn="xxx" wnlex="xxx">e</w>
  <w form="essa" lemma="esse" tag="DD0FS0" wnsyn="xxx" wnlex="xxx">essa</w>
  <w form="fogueira" lemma="fogueira" tag="NCFS000" wnsyn="07303335-n" wnlex="XXX">fogueira</w>
  <w form="," lemma="," tag="Fc" wnsyn="xxx" wnlex="xxx">,</w>
  <w form="que" lemma="que" tag="PR0CN00" wnsyn="xxx" wnlex="xxx">que</w>
  <w form="foi" lemma="ir" tag="VMIS3S0" wnsyn="01835496-v" wnlex="XXX">foi</w>
  <w form="a" lemma="o" tag="DA0FS0" wnsyn="xxx" wnlex="xxx">a</w>
  <w form="última" lemma="última" tag="NCFS000" wnsyn="xxx" wnlex="xxx">última</w>
  <w form="em" lemma="em" tag="SP" wnsyn="xxx" wnlex="xxx">em</w>
  <w form="Portugal" lemma="portugal" tag="NP00000" wnsyn="xxx" wnlex="xxx">Portugal</w>
  <w form="," lemma="," tag="Fc" wnsyn="xxx" wnlex="xxx">,</w>
  <w form="a" lemma="a" tag="SP" wnsyn="xxx" wnlex="xxx">a</w>
  <w form="o" lemma="o" tag="DA0MS0" wnsyn="xxx" wnlex="xxx">o</w>
  <w form="apagar" lemma="apagar" tag="VMN03S0" wnsyn="xxx" wnlex="xxx">apagar</w>
  <w form="se" lemma="se" tag="PP3CN00" wnsyn="xxx" wnlex="xxx">se</w>
  <w form="deixara" lemma="deixar" tag="VMIM1S0" wnsyn="00120316-v" wnlex="XXX">deixara</w>
  <w form="um" lemma="um" tag="DI0MS0" wnsyn="xxx" wnlex="xxx">um</w>
  <w form="sedimento" lemma="sedimento" tag="NCMS000" wnsyn="09428967-n" wnlex="XXX">sedimento</w>
  <w form="lodoso" lemma="lodoso" tag="AQ0MS00" wnsyn="02235826-a" wnlex="XXX">lodoso</w>
  <w form="em" lemma="em" tag="SP" wnsyn="xxx" wnlex="xxx">em</w>
  <w form="que" lemma="que" tag="PR0CN00" wnsyn="xxx" wnlex="xxx">que</w>
  <w form="a" lemma="o" tag="DA0FS0" wnsyn="xxx" wnlex="xxx">a</w>
  <w form="Providência" lemma="providência" tag="NP00000" wnsyn="01132327-n" wnlex="XXX">Providência</w>
  <w form="mandou" lemma="mandar" tag="VMIS3S0" wnsyn="01031256-v" wnlex="XXX">mandou</w>
  <w form="procurar" lemma="procurar" tag="VMN0000" wnsyn="02530167-v" wnlex="XXX">procurar</w>
  <w form="as" lemma="o" tag="DA0FP0" wnsyn="xxx" wnlex="xxx">as</w>
  <w form="carnes" lemma="carne" tag="NCFP000" wnsyn="07649854-n" wnlex="XXX">carnes</w>
  <w form="," lemma="," tag="Fc" wnsyn="xxx" wnlex="xxx">,</w>
  <w form="os" lemma="o" tag="DA0MP0" wnsyn="xxx" wnlex="xxx">os</w>
  <w form="ossos" lemma="osso" tag="NCMP000" wnsyn="05269901-n" wnlex="XXX">ossos</w>
  <w form="," lemma="," tag="Fc" wnsyn="xxx" wnlex="xxx">,</w>
  <w form="e" lemma="e" tag="CC" wnsyn="xxx" wnlex="xxx">e</w>
  <w form="me" lemma="me" tag="PP1CS00" wnsyn="xxx" wnlex="xxx">me</w>
  <w form="quer" lemma="querer" tag="VMIP3S0" wnsyn="01825237-v" wnlex="XXX">quer</w>
  <w form="parecer" lemma="parecer" tag="VMN0000" wnsyn="00010435-v" wnlex="XXX">parecer</w>
  <w form="que" lemma="que" tag="CS" wnsyn="xxx" wnlex="xxx">que</w>
  <w form="a" lemma="o" tag="DA0FS0" wnsyn="xxx" wnlex="xxx">a</w>
  <w form="alma" lemma="alma" tag="NCFS000" wnsyn="04632157-n" wnlex="XXX">alma</w>
  <w form="de" lemma="de" tag="SP" wnsyn="xxx" wnlex="xxx">de</w>
  <w form="o" lemma="o" tag="DA0MS0" wnsyn="xxx" wnlex="xxx">o</w>
  <w form="padre" lemma="padre" tag="NCMS000" wnsyn="10471250-n" wnlex="XXX">padre</w>
  <w form="Gabriel_Malagrida" lemma="gabriel_malagrida" tag="NP00000" wnsyn="xxx" wnlex="xxx">Gabriel_Malagrida</w>
  <w form="." lemma="." tag="Fp" wnsyn="xxx" wnlex="xxx">.</w>
</s>
<s>
  <w form="Aqui" lemma="aqui" tag="RG" wnsyn="00108647-r" wnlex="XXX">Aqui</w>
  <w form="está" lemma="estar" tag="VMIP3S0" wnsyn="02604760-v" wnlex="XXX">está</w>
  <w form="a" lemma="o" tag="DA0FS0" wnsyn="xxx" wnlex="xxx">a</w>
  <w form="Providência" lemma="providência" tag="NP00000" wnsyn="01132327-n" wnlex="XXX">Providência</w>
  <w form="." lemma="." tag="Fp" wnsyn="xxx" wnlex="xxx">.</w>
</s>
<s>
  <w form="Mas" lemma="mas" tag="CC" >Mas</w>
  <w form="quem" lemma="quem" tag="PT0CN00" wnsyn="xxx" wnlex="xxx">quem</w>
  <w form="deu" lemma="dar" tag="VMIS3S0" wnsyn="02230772-v" wnlex="XXX">deu</w>
  <w form="conta" lemma="conta" tag="NCFS000" wnsyn="06516955-n" wnlex="XXX">conta</w>
  <w form="de" lemma="de" tag="SP" wnsyn="xxx" wnlex="xxx">de</w>
  <w form="os" lemma="o" tag="DA0MP0" wnsyn="xxx" wnlex="xxx">os</w>
  <w form="milhares" lemma="milhar" tag="NCMP000" wnsyn="xxx" wnlex="xxx">milhares</w>
  <w form="de" lemma="de" tag="SP" wnsyn="xxx" wnlex="xxx">de</w>
  <w form="famílias" lemma="família" tag="NCFP000" wnsyn="08101937-n" wnlex="XXX">famílias</w>
  <w form="," lemma="," tag="Fc" wnsyn="xxx" wnlex="xxx">,</w>
  <w form="cujas" lemma="cujo" tag="PR0FP00" wnsyn="xxx" wnlex="xxx">cujas</w>
  <w form="cinzas" lemma="cinza" tag="NCFP000" wnsyn="14769160-n" wnlex="XXX">cinzas</w>
  <w form="levaram" lemma="levar" tag="VMIS3P0" wnsyn="00723545-v" wnlex="XXX">levaram</w>
  <w form="os" lemma="o" tag="DA0MP0" wnsyn="xxx" wnlex="xxx">os</w>
  <w form="quatro" lemma="4" tag="Z" wnsyn="xxx" wnlex="xxx">quatro</w>
  <w form="ventos" lemma="vento" tag="NCMP000" wnsyn="11525955-n" wnlex="XXX">ventos</w>
  <w form="de" lemma="de" tag="SP" wnsyn="xxx" wnlex="xxx">de</w>
  <w form="o" lemma="o" tag="DA0MS0" wnsyn="xxx" wnlex="xxx">o</w>
  <w form="céu" lemma="céu" tag="NCMS000" wnsyn="09436708-n" wnlex="XXX">céu</w>
  <w form="?" lemma="?" tag="Fit" wnsyn="xxx" wnlex="xxx">?</w>
</s>
<s>
  <w form="A" lemma="o" tag="DA0FS0" >A</w>
  <w form="Providência" lemma="providência" tag="NP00000" wnsyn="01132327-n" wnlex="XXX">Providência</w>
  <w form="não" lemma="não" tag="RN" wnsyn="00118531-r" wnlex="XXX">não</w>
  <w form="as" lemma="o" tag="PP3FPA0" wnsyn="xxx" wnlex="xxx">as</w>
  <w form="pediu" lemma="pedir" tag="VMIS3S0" wnsyn="00752764-v" wnlex="XXX">pediu</w>
  <w form="—" lemma="—" tag="Fz" wnsyn="xxx" wnlex="xxx">—</w>
  <w form="acrescenta" lemma="acrescentar" tag="VMIP3S0" wnsyn="00182406-v" wnlex="XXX">acrescenta</w>
  <w form="uma" lemma="um" tag="DI0FS0" wnsyn="xxx" wnlex="xxx">uma</w>
  <w form="blasfema" lemma="blasfemo" tag="AQ0FS00" wnsyn="xxx" wnlex="xxx">blasfema</w>
  <w form="filosofia" lemma="filosofia" tag="NCFS000" wnsyn="05943300-n" wnlex="XXX">filosofia</w>
  <w form="." lemma="." tag="Fp" wnsyn="xxx" wnlex="xxx">.</w>
</s>
<s>
  <w form="Pediu" lemma="pedir" tag="VMIS3S0" wnsyn="00752764-v" wnlex="XXX">Pediu</w>
  <w form="." lemma="." tag="Fp" wnsyn="xxx" wnlex="xxx">.</w>
</s>
<s>
  <w form="De" lemma="de" tag="SP" >De</w>
  <w form="estes" lemma="este" tag="DD0MP0" wnsyn="xxx" wnlex="xxx">estes</w>
  <w form="atascadeiros" lemma="atascadeiro" tag="NCMP000" wnsyn="xxx" wnlex="xxx">atascadeiros</w>
  <w form="de" lemma="de" tag="SP" wnsyn="xxx" wnlex="xxx">de</w>
  <w form="o" lemma="o" tag="DA0MS0" wnsyn="xxx" wnlex="xxx">o</w>
  <w form="mundo" lemma="mundo" tag="NCMS000" wnsyn="02472987-n" wnlex="XXX">mundo</w>
  <w form="não" lemma="não" tag="RN" wnsyn="00118531-r" wnlex="XXX">não</w>
  <w form="podemos" lemma="poder" tag="VMIP1P0" wnsyn="xxx" wnlex="xxx">podemos</w>
  <w form="desferir" lemma="desferir" tag="VMN0000" wnsyn="xxx" wnlex="xxx">desferir</w>
  <w form="o" lemma="o" tag="DA0MS0" wnsyn="xxx" wnlex="xxx">o</w>
  <w form="voo" lemma="voo" tag="NCMS000" wnsyn="00302394-n" wnlex="XXX">voo</w>
  <w form="lá" lemma="lá" tag="RG" wnsyn="00082308-r" wnlex="XXX">lá</w>
  <w form="para_onde" lemma="para_onde" tag="RG" wnsyn="xxx" wnlex="xxx">para_onde</w>
  <w form="essas" lemma="esse" tag="DD0FP0" wnsyn="xxx" wnlex="xxx">essas</w>
  <w form="contas" lemma="conta" tag="NCFP000" wnsyn="06516955-n" wnlex="XXX">contas</w>
  <w form="se" lemma="se" tag="PP3CN00" wnsyn="xxx" wnlex="xxx">se</w>
  <w form="pedem" lemma="pedir" tag="VMIP3P0" wnsyn="00752764-v" wnlex="XXX">pedem</w>
  <w form=";" lemma=";" tag="Fx" wnsyn="xxx" wnlex="xxx">;</w>
  <w form="cremos" lemma="crer" tag="VMIP1P0" wnsyn="00688377-v" wnlex="XXX">cremos</w>
  <w form="," lemma="," tag="Fc" wnsyn="xxx" wnlex="xxx">,</w>
  <w form="porém" lemma="porém" tag="CC" wnsyn="xxx" wnlex="xxx">porém</w>
  <w form="," lemma="," tag="Fc" wnsyn="xxx" wnlex="xxx">,</w>
  <w form="com" lemma="com" tag="SP" wnsyn="xxx" wnlex="xxx">com</w>
  <w form="a" lemma="o" tag="DA0FS0" wnsyn="xxx" wnlex="xxx">a</w>
  <w form="mais" lemma="mais" tag="RG" wnsyn="00029367-r" wnlex="XXX">mais</w>
  <w form="pia" lemma="pio" tag="AQ0FS00" wnsyn="xxx" wnlex="xxx">pia</w>
  <w form="racionalidade" lemma="racionalidade" tag="NCFS000" wnsyn="04784978-n" wnlex="XXX">racionalidade</w>
  <w form="," lemma="," tag="Fc" wnsyn="xxx" wnlex="xxx">,</w>
  <w form="que" lemma="que" tag="CS" wnsyn="xxx" wnlex="xxx">que</w>
  <w form="os" lemma="o" tag="DA0MP0" wnsyn="xxx" wnlex="xxx">os</w>
  <w form="filhos" lemma="filho" tag="NCMP000" wnsyn="10624074-n" wnlex="XXX">filhos</w>
  <w form="de" lemma="de" tag="SP" wnsyn="xxx" wnlex="xxx">de</w>
  <w form="S._Domingos" lemma="s._domingos" tag="NP00000" wnsyn="xxx" wnlex="xxx">S._Domingos</w>
  <w form="e" lemma="e" tag="CC" wnsyn="xxx" wnlex="xxx">e</w>
  <w form="filhos" lemma="filho" tag="NCMP000" wnsyn="10624074-n" wnlex="XXX">filhos</w>
  <w form="de" lemma="de" tag="SP" wnsyn="xxx" wnlex="xxx">de</w>
  <w form="os" lemma="o" tag="DA0MP0" wnsyn="xxx" wnlex="xxx">os</w>
  <w form="santos" lemma="santo" tag="AQ0MP00" wnsyn="02053818-a" wnlex="XXX">santos</w>
  <w form="pontífices" lemma="pontífice" tag="NCCP000" wnsyn="xxx" wnlex="xxx">pontífices</w>
  <w form="foram" lemma="ir" tag="VMIS3P0" wnsyn="01835496-v" wnlex="XXX">foram</w>
  <w form="chamados" lemma="chamar" tag="VMP00PM" wnsyn="01028748-v" wnlex="XXX">chamados</w>
  <w form="a" lemma="o" tag="DA0FS0" wnsyn="xxx" wnlex="xxx">a</w>
  <w form="contas" lemma="conta" tag="NCFP000" wnsyn="06516955-n" wnlex="XXX">contas</w>
  <w form="," lemma="," tag="Fc" wnsyn="xxx" wnlex="xxx">,</w>
  <w form="e" lemma="e" tag="CC" wnsyn="xxx" wnlex="xxx">e</w>
  <w form="as" lemma="o" tag="PP3FPA0" wnsyn="xxx" wnlex="xxx">as</w>
  <w form="deram" lemma="dar" tag="VMIS3P0" wnsyn="02230772-v" wnlex="XXX">deram</w>
  <w form="como" lemma="como" tag="CS" wnsyn="xxx" wnlex="xxx">como</w>
  <w form="criminosos" lemma="criminoso" tag="NCMP000" wnsyn="xxx" wnlex="xxx">criminosos</w>
  <w form="de" lemma="de" tag="SP" wnsyn="xxx" wnlex="xxx">de</w>
  <w form="um" lemma="um" tag="DI0MS0" wnsyn="xxx" wnlex="xxx">um</w>
  <w form="período" lemma="período" tag="NCMS000" wnsyn="15248564-n" wnlex="XXX">período</w>
  <w form="de" lemma="de" tag="SP" wnsyn="xxx" wnlex="xxx">de</w>
  <w form="o" lemma="o" tag="DA0MS0" wnsyn="xxx" wnlex="xxx">o</w>
  <w form="mundo" lemma="mundo" tag="NCMS000" wnsyn="02472987-n" wnlex="XXX">mundo</w>
  <w form="em" lemma="em" tag="SP" wnsyn="xxx" wnlex="xxx">em</w>
  <w form="que" lemma="que" tag="PR0CN00" wnsyn="xxx" wnlex="xxx">que</w>
  <w form="a" lemma="o" tag="DA0FS0" wnsyn="xxx" wnlex="xxx">a</w>
  <w form="legislação" lemma="legislação" tag="NCFS000" wnsyn="06535222-n" wnlex="XXX">legislação</w>
  <w form="civil" lemma="civil" tag="AQ0CS00" wnsyn="01517921-a" wnlex="XXX">civil</w>
  <w form="não" lemma="não" tag="RN" wnsyn="00118531-r" wnlex="XXX">não</w>
  <w form="era" lemma="ser" tag="VMII1S0" wnsyn="02604760-v" wnlex="XXX">era</w>
  <w form="mais" lemma="mais" tag="RG" wnsyn="00029367-r" wnlex="XXX">mais</w>
  <w form="misericordiosa" lemma="misericordioso" tag="AQ0FS00" wnsyn="01507134-a" wnlex="XXX">misericordiosa</w>
  <w form="que" lemma="que" tag="CS" wnsyn="xxx" wnlex="xxx">que</w>
  <w form="a" lemma="o" tag="DA0FS0" wnsyn="xxx" wnlex="xxx">a</w>
  <w form="eclesiástica" lemma="eclesiástico" tag="AQ0FS00" wnsyn="02899486-a" wnlex="XXX">eclesiástica</w>
  <w form="." lemma="." tag="Fp" wnsyn="xxx" wnlex="xxx">.</w>
</s>
<s>
  <w form="Eu" lemma="eu" tag="PP1CSN0" >Eu</w>
  <w form="creio" lemma="crer" tag="VMIP1S0" wnsyn="00688377-v" wnlex="XXX">creio</w>
  <w form="que" lemma="que" tag="CS" wnsyn="xxx" wnlex="xxx">que</w>
  <w form="ninguém" lemma="ninguém" tag="PI0CN00" wnsyn="xxx" wnlex="xxx">ninguém</w>
  <w form="tirou" lemma="tirar" tag="VMIS3S0" wnsyn="00173338-v" wnlex="XXX">tirou</w>
  <w form="uma" lemma="um" tag="DI0FS0" wnsyn="xxx" wnlex="xxx">uma</w>
  <w form="vida" lemma="vida" tag="NCFS000" wnsyn="00017222-n" wnlex="XXX">vida</w>
  <w form="que" lemma="que" tag="PR0CN00" wnsyn="xxx" wnlex="xxx">que</w>
  <w form="não" lemma="não" tag="RN" wnsyn="00118531-r" wnlex="XXX">não</w>
  <w form="respondesse" lemma="responder" tag="VMSI3S0" wnsyn="00717358-v" wnlex="XXX">respondesse</w>
  <w form="por" lemma="por" tag="SP" wnsyn="xxx" wnlex="xxx">por</w>
  <w form="ela" lemma="ele" tag="PP3FS00" wnsyn="xxx" wnlex="xxx">ela</w>
  <w form="quando" lemma="quando" tag="RG" wnsyn="xxx" wnlex="xxx">quando</w>
  <w form="o" lemma="o" tag="DA0MS0" wnsyn="xxx" wnlex="xxx">o</w>
  <w form="nome" lemma="nome" tag="NCMS000" wnsyn="06333653-n" wnlex="XXX">nome</w>
  <w form="de" lemma="de" tag="SP" wnsyn="xxx" wnlex="xxx">de</w>
  <w form="o" lemma="o" tag="DA0MS0" wnsyn="xxx" wnlex="xxx">o</w>
  <w form="assassinado" lemma="assassinar" tag="VMP00SM" wnsyn="02482425-v" wnlex="XXX">assassinado</w>
  <w form="fosse" lemma="fossar" tag="VMSP1S0" wnsyn="xxx" wnlex="xxx">fosse</w>
  <w form="lido" lemma="ler" tag="VMP00SM" wnsyn="00625119-v" wnlex="XXX">lido</w>
  <w form="em" lemma="em" tag="SP" wnsyn="xxx" wnlex="xxx">em</w>
  <w form="a" lemma="o" tag="DA0FS0" wnsyn="xxx" wnlex="xxx">a</w>
  <w form="lista" lemma="lista" tag="NCFS000" wnsyn="06481320-n" wnlex="XXX">lista</w>
  <w form="de" lemma="de" tag="SP" wnsyn="xxx" wnlex="xxx">de</w>
  <w form="o" lemma="o" tag="DA0MS0" wnsyn="xxx" wnlex="xxx">o</w>
  <w form="seu" lemma="seu" tag="DP3MSS" wnsyn="xxx" wnlex="xxx">seu</w>
  <w form="Criador" lemma="criador" tag="NP00000" wnsyn="09614315-n" wnlex="XXX">Criador</w>
  <w form="." lemma="." tag="Fp" wnsyn="xxx" wnlex="xxx">.</w>
</s>
<s>
  <w form="E" lemma="e" tag="CC" >E</w>
  <w form="por" lemma="por" tag="SP" wnsyn="xxx" wnlex="xxx">por</w>
  <w form="isso" lemma="isso" tag="PD0NN00" wnsyn="xxx" wnlex="xxx">isso</w>
  <w form="pergunto" lemma="perguntar" tag="VMIP1S0" wnsyn="00784342-v" wnlex="XXX">pergunto</w>
  <w form="a" lemma="a" tag="SP" wnsyn="xxx" wnlex="xxx">a</w>
  <w form="os" lemma="o" tag="DA0MP0" wnsyn="xxx" wnlex="xxx">os</w>
  <w form="oráculos" lemma="oráculo" tag="NCMP000" wnsyn="06750339-n" wnlex="XXX">oráculos</w>
  <w form="de" lemma="de" tag="SP" wnsyn="xxx" wnlex="xxx">de</w>
  <w form="os" lemma="o" tag="DA0MP0" wnsyn="xxx" wnlex="xxx">os</w>
  <w form="nossos" lemma="nosso" tag="DP1MPP" wnsyn="xxx" wnlex="xxx">nossos</w>
  <w form="dias" lemma="dia" tag="NCMP000" wnsyn="15155220-n" wnlex="XXX">dias</w>
  <w form="se" lemma="se" tag="CS" wnsyn="xxx" wnlex="xxx">se</w>
  <w form="os" lemma="o" tag="DA0MP0" wnsyn="xxx" wnlex="xxx">os</w>
  <w form="caprichos" lemma="capricho" tag="NCMP000" wnsyn="07490579-n" wnlex="XXX">caprichos</w>
  <w form="de" lemma="de" tag="SP" wnsyn="xxx" wnlex="xxx">de</w>
  <w form="os" lemma="o" tag="DA0MP0" wnsyn="xxx" wnlex="xxx">os</w>
  <w form="reis" lemma="rei" tag="NCMP000" wnsyn="10231515-n" wnlex="XXX">reis</w>
  <w form="não" lemma="não" tag="RN" wnsyn="00118531-r" wnlex="XXX">não</w>
  <w form="têm" lemma="ter" tag="VMIP3P0" wnsyn="00065639-v" wnlex="XXX">têm</w>
  <w form="que" lemma="que" tag="CS" wnsyn="xxx" wnlex="xxx">que</w>
  <w form="dizer" lemma="dizer" tag="VMN0000" wnsyn="00963570-v" wnlex="XXX">dizer</w>
  <w form="de" lemma="de" tag="SP" wnsyn="xxx" wnlex="xxx">de</w>
  <w form="a" lemma="o" tag="DA0FS0" wnsyn="xxx" wnlex="xxx">a</w>
  <w form="sua" lemma="seu" tag="DP3FSS" wnsyn="xxx" wnlex="xxx">sua</w>
  <w form="justiça" lemma="justiça" tag="NCFS000" wnsyn="00694681-n" wnlex="XXX">justiça</w>
  <w form="," lemma="," tag="Fc" wnsyn="xxx" wnlex="xxx">,</w>
  <w form="quando" lemma="quando" tag="RG" wnsyn="xxx" wnlex="xxx">quando</w>
  <w form="lhes" lemma="lhe" tag="PP3CPD0" wnsyn="xxx" wnlex="xxx">lhes</w>
  <w form="perguntarem" lemma="perguntar" tag="VMN03P0" wnsyn="00784342-v" wnlex="XXX">perguntarem</w>
  <w form="porque" lemma="porque" tag="CS" wnsyn="xxx" wnlex="xxx">porque</w>
  <w form="alvejam" lemma="alvejar" tag="VMIP3P0" wnsyn="00280301-v" wnlex="XXX">alvejam</w>
  <w form="ainda" lemma="ainda" tag="RG" wnsyn="00047534-r" wnlex="XXX">ainda</w>
  <w form="as" lemma="o" tag="DA0FP0" wnsyn="xxx" wnlex="xxx">as</w>
  <w form="ossadas" lemma="ossada" tag="NCFP000" wnsyn="xxx" wnlex="xxx">ossadas</w>
  <w form="em" lemma="em" tag="SP" wnsyn="xxx" wnlex="xxx">em</w>
  <w form="os" lemma="o" tag="DA0MP0" wnsyn="xxx" wnlex="xxx">os</w>
  <w form="descampados" lemma="descampado" tag="NCMP000" wnsyn="xxx" wnlex="xxx">descampados</w>
  <w form="em" lemma="em" tag="SP" wnsyn="xxx" wnlex="xxx">em</w>
  <w form="que" lemma="que" tag="PR0CN00" wnsyn="xxx" wnlex="xxx">que</w>
  <w form="passaram" lemma="passar" tag="VMIS3P0" wnsyn="01212230-v" wnlex="XXX">passaram</w>
  <w form="os" lemma="o" tag="DA0MP0" wnsyn="xxx" wnlex="xxx">os</w>
  <w form="reis" lemma="rei" tag="NCMP000" wnsyn="10231515-n" wnlex="XXX">reis</w>
  <w form="," lemma="," tag="Fc" wnsyn="xxx" wnlex="xxx">,</w>
  <w form="a" lemma="a" tag="SP" wnsyn="xxx" wnlex="xxx">a</w>
  <w form="a" lemma="o" tag="DA0FS0" wnsyn="xxx" wnlex="xxx">a</w>
  <w form="frente" lemma="frente" tag="NCFS000" wnsyn="08573674-n" wnlex="XXX">frente</w>
  <w form="de" lemma="de" tag="SP" wnsyn="xxx" wnlex="xxx">de</w>
  <w form="as" lemma="o" tag="DA0FP0" wnsyn="xxx" wnlex="xxx">as</w>
  <w form="suas" lemma="seu" tag="DP3FSP" wnsyn="xxx" wnlex="xxx">suas</w>
  <w form="reses" lemma="rês" tag="NCFP000" wnsyn="xxx" wnlex="xxx">reses</w>
  <w form="." lemma="." tag="Fp" wnsyn="xxx" wnlex="xxx">.</w>
</s>
<s>
  <w form="Não" lemma="não" tag="RN" wnsyn="00118531-r" wnlex="XXX">Não</w>
  <w form="sei" lemma="saber" tag="VMIP1S0" wnsyn="00594621-v" wnlex="XXX">sei</w>
  <w form="qual" lemma="qual" tag="PR0CS00" wnsyn="xxx" wnlex="xxx">qual</w>
  <w form="razão" lemma="razão" tag="NCFS000" wnsyn="09178999-n" wnlex="XXX">razão</w>
  <w form="haja" lemma="haver" tag="VMSP1S0" wnsyn="02616713-v" wnlex="XXX">haja</w>
  <w form="aí" lemma="aí" tag="RG" wnsyn="00082308-r" wnlex="XXX">aí</w>
  <w form="que" lemma="que" tag="CS" wnsyn="xxx" wnlex="xxx">que</w>
  <w form="legitime" lemma="legitimar" tag="VMSP3S0" wnsyn="02481436-v" wnlex="XXX">legitime</w>
  <w form="o" lemma="o" tag="DA0MS0" wnsyn="xxx" wnlex="xxx">o</w>
  <w form="morrer" lemma="morrer" tag="VMN0000" wnsyn="00358431-v" wnlex="XXX">morrer</w>
  <w form="de" lemma="de" tag="SP" wnsyn="xxx" wnlex="xxx">de</w>
  <w form="os" lemma="o" tag="DA0MP0" wnsyn="xxx" wnlex="xxx">os</w>
  <w form="que" lemma="que" tag="PR0CN00" wnsyn="xxx" wnlex="xxx">que</w>
  <w form="pelejam" lemma="pelejar" tag="VMIP3P0" wnsyn="02407338-v" wnlex="XXX">pelejam</w>
  <w form=";" lemma=";" tag="Fx" wnsyn="xxx" wnlex="xxx">;</w>
  <w form="contra" lemma="contra" tag="SP" wnsyn="xxx" wnlex="xxx">contra</w>
  <w form="uma" lemma="um" tag="DI0FS0" wnsyn="xxx" wnlex="xxx">uma</w>
  <w form="bandeira" lemma="bandeira" tag="NCFS000" wnsyn="03354903-n" wnlex="XXX">bandeira</w>
  <w form=";" lemma=";" tag="Fx" wnsyn="xxx" wnlex="xxx">;</w>
  <w form="e" lemma="e" tag="CC" wnsyn="xxx" wnlex="xxx">e</w>
  <w form="se" lemma="se" tag="CS" wnsyn="xxx" wnlex="xxx">se</w>
  <w form="deplore" lemma="deplorar" tag="VMSP3S0" wnsyn="00826333-v" wnlex="XXX">deplore</w>
  <w form="sobre" lemma="sobre" tag="SP" wnsyn="xxx" wnlex="xxx">sobre</w>
  <w form="a" lemma="o" tag="DA0FS0" wnsyn="xxx" wnlex="xxx">a</w>
  <w form="página" lemma="página" tag="NCFS000" wnsyn="06256697-n" wnlex="XXX">página</w>
  <w form="tarjada" lemma="tarjar" tag="VMP00SF" wnsyn="xxx" wnlex="xxx">tarjada</w>
  <w form="de" lemma="de" tag="SP" wnsyn="xxx" wnlex="xxx">de</w>
  <w form="os" lemma="o" tag="DA0MP0" wnsyn="xxx" wnlex="xxx">os</w>
  <w form="que" lemma="que" tag="PR0CN00" wnsyn="xxx" wnlex="xxx">que</w>
  <w form="caíram" lemma="cair" tag="VMIS3P0" wnsyn="01976841-v" wnlex="XXX">caíram</w>
  <w form="em" lemma="em" tag="SP" wnsyn="xxx" wnlex="xxx">em</w>
  <w form="as" lemma="o" tag="DA0FP0" wnsyn="xxx" wnlex="xxx">as</w>
  <w form="lutas" lemma="luta" tag="NCFP000" wnsyn="01170962-n" wnlex="XXX">lutas</w>
  <w form="religiosas" lemma="religioso" tag="AQ0FP00" wnsyn="01783158-a" wnlex="XXX">religiosas</w>
  <w form="," lemma="," tag="Fc" wnsyn="xxx" wnlex="xxx">,</w>
  <w form="mais_ou_menos" lemma="mais_ou_menos" tag="RG" wnsyn="xxx" wnlex="xxx">mais_ou_menos</w>
  <w form="covardemente" lemma="covarde" tag="RG" wnsyn="xxx" wnlex="xxx">covardemente</w>
  <w form="assassinados" lemma="assassinar" tag="VMP00PM" wnsyn="02482425-v" wnlex="XXX">assassinados</w>
  <w form="." lemma="." tag="Fp" wnsyn="xxx" wnlex="xxx">.</w>
</s>
<s>
  <w form="De" lemma="de" tag="SP" >De</w>
  <w form="cadáver" lemma="cadáver" tag="NCMS000" wnsyn="05216365-n" wnlex="XXX">cadáver</w>
  <w form="a" lemma="a" tag="SP" wnsyn="xxx" wnlex="xxx">a</w>
  <w form="cadáver" lemma="cadáver" tag="NCMS000" wnsyn="05216365-n" wnlex="XXX">cadáver</w>
  <w form="não" lemma="não" tag="RN" wnsyn="00118531-r" wnlex="XXX">não</w>
  <w form="há" lemma="haver" tag="VMIP3S0" wnsyn="02616713-v" wnlex="XXX">há</w>
  <w form="distinção" lemma="distinção" tag="NCFS000" wnsyn="04749572-n" wnlex="XXX">distinção</w>
  <w form="." lemma="." tag="Fp" wnsyn="xxx" wnlex="xxx">.</w>
</s>
<s>
  <w form="É" lemma="ser" tag="VMIP3S0" wnsyn="02604760-v" wnlex="XXX">É</w>
  <w form="tudo" lemma="tudo" tag="PI0NN00" wnsyn="xxx" wnlex="xxx">tudo</w>
  <w form="o" lemma="o" tag="DA0MS0" wnsyn="xxx" wnlex="xxx">o</w>
  <w form="mesmo" lemma="mesmo" tag="RG" wnsyn="xxx" wnlex="xxx">mesmo</w>
  <w form="açougue" lemma="açougue" tag="NCMS000" wnsyn="02666943-n" wnlex="XXX">açougue</w>
  <w form="." lemma="." tag="Fp" wnsyn="xxx" wnlex="xxx">.</w></s>
</wrapper>